{"errors":[],"warnings":[],"namedChunkGroups":{"polyfill":{"chunks":[1,5],"assets":["webpack-runtime-ffc6310e37e3a97f8b8b.js","webpack-runtime-ffc6310e37e3a97f8b8b.js.map","polyfill-b26ca15045427b9506aa.js","polyfill-b26ca15045427b9506aa.js.map"],"children":{},"childAssets":{}},"app":{"chunks":[1,0,4,2],"assets":["webpack-runtime-ffc6310e37e3a97f8b8b.js","webpack-runtime-ffc6310e37e3a97f8b8b.js.map","styles.aa1529ccd488e80829e6.css","styles-407fe62976dc5310c43e.js","styles-407fe62976dc5310c43e.js.map","framework-06f646d936b841f99ebd.js","framework-06f646d936b841f99ebd.js.map","app-913af3b52f77500888d0.js","app-913af3b52f77500888d0.js.map"],"children":{},"childAssets":{}},"component---src-pages-index-tsx":{"chunks":[0,3],"assets":["styles.aa1529ccd488e80829e6.css","styles-407fe62976dc5310c43e.js","styles-407fe62976dc5310c43e.js.map","component---src-pages-index-tsx-9f5f9cdb582717aeb1e7.js","component---src-pages-index-tsx-9f5f9cdb582717aeb1e7.js.map"],"children":{},"childAssets":{}}},"assetsByChunkName":{"polyfill":["webpack-runtime-ffc6310e37e3a97f8b8b.js","polyfill-b26ca15045427b9506aa.js"],"app":["webpack-runtime-ffc6310e37e3a97f8b8b.js","styles.aa1529ccd488e80829e6.css","styles-407fe62976dc5310c43e.js","framework-06f646d936b841f99ebd.js","app-913af3b52f77500888d0.js"],"component---src-pages-index-tsx":["styles.aa1529ccd488e80829e6.css","styles-407fe62976dc5310c43e.js","component---src-pages-index-tsx-9f5f9cdb582717aeb1e7.js"]}}